<?xml version="1.0" encoding="UTF-8" standalone="no"?>
<database name="modos_db" schema="osmdata" type="PostgreSQL - 10.12 (Ubuntu 10.12-0ubuntu0.18.04.1)">
   <tables>
      <table name="osm_edges" numRows="22523" remarks="" schema="osmdata" type="TABLE">
         <column autoUpdated="true" defaultValue="nextval('osm_edges_ogc_fid_seq'::regclass)" digits="0" id="0" name="ogc_fid" nullable="false" remarks="" size="10" type="serial"/>
         <column autoUpdated="false" digits="0" id="1" name="u" nullable="true" remarks="" size="2147483647" type="varchar"/>
         <column autoUpdated="false" digits="0" id="2" name="v" nullable="true" remarks="" size="2147483647" type="varchar"/>
         <column autoUpdated="false" digits="0" id="3" name="key" nullable="true" remarks="" size="2147483647" type="varchar"/>
         <column autoUpdated="false" digits="0" id="4" name="osmid" nullable="true" remarks="" size="2147483647" type="varchar"/>
         <column autoUpdated="false" digits="0" id="5" name="highway" nullable="true" remarks="" size="2147483647" type="varchar"/>
         <column autoUpdated="false" digits="0" id="6" name="name" nullable="true" remarks="" size="2147483647" type="varchar"/>
         <column autoUpdated="false" digits="0" id="7" name="oneway" nullable="true" remarks="" size="2147483647" type="varchar"/>
         <column autoUpdated="false" digits="0" id="8" name="length" nullable="true" remarks="" size="2147483647" type="varchar"/>
         <column autoUpdated="false" digits="0" id="9" name="from" nullable="true" remarks="" size="2147483647" type="varchar"/>
         <column autoUpdated="false" digits="0" id="10" name="to" nullable="true" remarks="" size="2147483647" type="varchar"/>
         <column autoUpdated="false" digits="0" id="11" name="maxspeed" nullable="true" remarks="" size="2147483647" type="varchar"/>
         <column autoUpdated="false" digits="0" id="12" name="lit" nullable="true" remarks="" size="2147483647" type="varchar"/>
         <column autoUpdated="false" digits="0" id="13" name="surface" nullable="true" remarks="" size="2147483647" type="varchar"/>
         <column autoUpdated="false" digits="0" id="14" name="bicycle" nullable="true" remarks="" size="2147483647" type="varchar"/>
         <column autoUpdated="false" digits="0" id="15" name="cycleway" nullable="true" remarks="" size="2147483647" type="varchar"/>
         <column autoUpdated="false" digits="0" id="16" name="access" nullable="true" remarks="" size="2147483647" type="varchar"/>
         <column autoUpdated="false" digits="0" id="17" name="foot" nullable="true" remarks="" size="2147483647" type="varchar"/>
         <column autoUpdated="false" digits="0" id="18" name="motor_vehicle" nullable="true" remarks="" size="2147483647" type="varchar"/>
         <column autoUpdated="false" digits="0" id="19" name="width" nullable="true" remarks="" size="2147483647" type="varchar"/>
         <column autoUpdated="false" digits="0" id="20" name="service" nullable="true" remarks="" size="2147483647" type="varchar"/>
         <column autoUpdated="false" digits="0" id="21" name="incline" nullable="true" remarks="" size="2147483647" type="varchar"/>
         <column autoUpdated="false" digits="0" id="22" name="smoothness" nullable="true" remarks="" size="2147483647" type="varchar"/>
         <column autoUpdated="false" digits="0" id="23" name="crossing" nullable="true" remarks="" size="2147483647" type="varchar"/>
         <column autoUpdated="false" digits="0" id="24" name="footway" nullable="true" remarks="" size="2147483647" type="varchar"/>
         <column autoUpdated="false" digits="0" id="25" name="tactile_paving" nullable="true" remarks="" size="2147483647" type="varchar"/>
         <column autoUpdated="false" digits="0" id="26" name="horse" nullable="true" remarks="" size="2147483647" type="varchar"/>
         <column autoUpdated="false" digits="0" id="27" name="tracktype" nullable="true" remarks="" size="2147483647" type="varchar"/>
         <column autoUpdated="false" digits="0" id="28" name="motorcycle" nullable="true" remarks="" size="2147483647" type="varchar"/>
         <column autoUpdated="false" digits="0" id="29" name="vehicle" nullable="true" remarks="" size="2147483647" type="varchar"/>
         <column autoUpdated="false" digits="0" id="30" name="bridge" nullable="true" remarks="" size="2147483647" type="varchar"/>
         <column autoUpdated="false" digits="0" id="31" name="layer" nullable="true" remarks="" size="2147483647" type="varchar"/>
         <column autoUpdated="false" digits="0" id="32" name="sidewalk" nullable="true" remarks="" size="2147483647" type="varchar"/>
         <column autoUpdated="false" digits="0" id="33" name="noexit" nullable="true" remarks="" size="2147483647" type="varchar"/>
         <column autoUpdated="false" digits="0" id="34" name="tunnel" nullable="true" remarks="" size="2147483647" type="varchar"/>
         <column autoUpdated="false" digits="0" id="35" name="wheelchair" nullable="true" remarks="" size="2147483647" type="varchar"/>
         <column autoUpdated="false" digits="0" id="36" name="handrail" nullable="true" remarks="" size="2147483647" type="varchar"/>
         <column autoUpdated="false" digits="0" id="37" name="description" nullable="true" remarks="" size="2147483647" type="varchar"/>
         <column autoUpdated="false" digits="0" id="38" name="step_count" nullable="true" remarks="" size="2147483647" type="varchar"/>
         <column autoUpdated="false" digits="0" id="39" name="railway" nullable="true" remarks="" size="2147483647" type="varchar"/>
         <column autoUpdated="false" digits="0" id="40" name="train" nullable="true" remarks="" size="2147483647" type="varchar"/>
         <column autoUpdated="false" digits="0" id="41" name="kerb" nullable="true" remarks="" size="2147483647" type="varchar"/>
         <column autoUpdated="false" digits="0" id="42" name="geom" nullable="true" remarks="" size="2147483647" type="geometry"/>
         <primaryKey column="ogc_fid" sequenceNumberInPK="1"/>
         <index name="osm_edges_pkey" unique="true">
            <column ascending="true" name="ogc_fid"/>
         </index>
         <index name="osm_edges_geom_geom_idx" unique="false">
            <column ascending="true" name="geom"/>
         </index>
         <index name="osmdata_edges_geom_idx" unique="false">
            <column ascending="true" name="geom"/>
         </index>
      </table>
      <table name="osm_nodes" numRows="21261" remarks="" schema="osmdata" type="TABLE">
         <column autoUpdated="true" defaultValue="nextval('osm_nodes_ogc_fid_seq'::regclass)" digits="0" id="0" name="ogc_fid" nullable="false" remarks="" size="10" type="serial"/>
         <column autoUpdated="false" digits="17" id="1" name="y" nullable="true" remarks="" size="17" type="float8"/>
         <column autoUpdated="false" digits="17" id="2" name="x" nullable="true" remarks="" size="17" type="float8"/>
         <column autoUpdated="false" digits="0" id="3" name="osmid" nullable="true" remarks="" size="19" type="int8"/>
         <column autoUpdated="false" digits="0" id="4" name="highway" nullable="true" remarks="" size="2147483647" type="varchar"/>
         <column autoUpdated="false" digits="0" id="5" name="geom" nullable="true" remarks="" size="2147483647" type="geometry"/>
         <primaryKey column="ogc_fid" sequenceNumberInPK="1"/>
         <index name="osm_nodes_pkey" unique="true">
            <column ascending="true" name="ogc_fid"/>
         </index>
         <index name="osm_nodes_geom_geom_idx" unique="false">
            <column ascending="true" name="geom"/>
         </index>
         <index name="osmdata_nodes_geom_idx" unique="false">
            <column ascending="true" name="geom"/>
         </index>
      </table>
   </tables>
</database>
